effis/__init__.py
effis/composition/__init__.py
effis/composition/application.py
effis/composition/backup.py
effis/composition/campaign.py
effis/composition/log.py
effis/composition/runner.py
effis/composition/util.py
effis/composition/workflow.py
effis/runtime/BackupGlobus.py
effis/runtime/EffisSubmit.py
effis/runtime/__init__.py
effis/runtime/globus.py
effis/shim/__init__.py
effis/shim/gx_omas.py
effis/shim/nc.py
effis/shim/omas_adios.py
effis/shim/vmec_omas.py
effis-2.0.0.dist-info/licenses/LICENSE
effis-2.0.0.dist-info/METADATA
effis-2.0.0.dist-info/WHEEL
effis-2.0.0.dist-info/entry_points.txt
effis-2.0.0.dist-info/top_level.txt
effis-2.0.0.dist-info/RECORD
