Metadata-Version: 2.4
Name: effis
Version: 2.0.0
Summary: EFFIS workflow manager
Author-email: Eric Suchyta <eric.d.suchyta@gmail.com>
License-File: LICENSE
Requires-Dist: dill
Requires-Dist: globus_sdk
Requires-Dist: pyyaml
Requires-Dist: colorama
Requires-Dist: omas
Provides-Extra: test
Requires-Dist: pytest; extra == "test"
Dynamic: license-file
